MANIFEST.in
README
README.md
setup.py
emacsql/__init__.py
emacsql/main.py
emacsql.egg-info/PKG-INFO
emacsql.egg-info/SOURCES.txt
emacsql.egg-info/dependency_links.txt
emacsql.egg-info/entry_points.txt
emacsql.egg-info/requires.txt
emacsql.egg-info/top_level.txt