Metadata-Version: 1.0
Name: emacsql
Version: 0.1.1
Summary: Edit a slice of a SQL database in emacs
Home-page: https://github.com/paulfitz/emacsql
Author: Paul Fitzpatrick
Author-email: paulfitz@alum.mit.edu
License: UNKNOWN
Platform: UNKNOWN
